google_drive_id_extractor/__init__.py
google_drive_id_extractor-1.2.0.dist-info/METADATA
google_drive_id_extractor-1.2.0.dist-info/WHEEL
google_drive_id_extractor-1.2.0.dist-info/top_level.txt
google_drive_id_extractor-1.2.0.dist-info/RECORD
