Metadata-Version: 2.1
Name: google_drive_id_extractor
Version: 1.2.0
Summary: This will extract the Google Drive file ID from any provided Google Drive link, making it easy to retrieve the ID programmatically. It's lightweight, simple to use, and supports various Google Drive link formats.
Home-page: https://toolsforfree.com/
Author: Kazim
Author-email: kazimshah39@gmail.com
Requires-Python: >=3.6
